GasNetSim/README.md
GasNetSim/__init__.py
GasNetSim/components/__init__.py
GasNetSim/components/compressor.py
GasNetSim/components/network.py
GasNetSim/components/node.py
GasNetSim/components/pipeline.py
GasNetSim/components/storage.py
GasNetSim/components/gas_mixture/__init__.py
GasNetSim/components/gas_mixture/gas_mixture.py
GasNetSim/components/gas_mixture/heating_value.py
GasNetSim/components/gas_mixture/typical_mixture_composition.py
GasNetSim/components/gas_mixture/viscosity.py
GasNetSim/components/gas_mixture/GERG2008/__init__.py
GasNetSim/components/gas_mixture/GERG2008/gerg2008.py
GasNetSim/components/gas_mixture/GERG2008/gerg2008_constants.py
GasNetSim/components/gas_mixture/GERG2008/gerg2008_numba.py
GasNetSim/components/gas_mixture/GERG2008/setup.py
GasNetSim/components/gas_mixture/functions/viscosity_methods/base_method.py
GasNetSim/components/gas_mixture/functions/viscosity_methods/herning_zipperer.py
GasNetSim/components/gas_mixture/functions/viscosity_methods/lucas.py
GasNetSim/components/utils/__init__.py
GasNetSim/components/utils/create_network.py
GasNetSim/components/utils/cuda_support.py
GasNetSim/components/utils/graph.py
GasNetSim/components/utils/initialization_strategies.py
GasNetSim/components/utils/network_diagnostics.py
GasNetSim/components/utils/plot_functions.py
GasNetSim/components/utils/utils.py
GasNetSim/components/utils/pipeline_function/__init__.py
GasNetSim/components/utils/pipeline_function/flow_rate.py
GasNetSim/components/utils/pipeline_function/friction_factor.py
GasNetSim/components/utils/pipeline_function/outlet_temperature.py
GasNetSim/profile/__init__.py
GasNetSim/profile/StandardLoadProfile/__init__.py
GasNetSim/profile/StandardLoadProfile/data_cleaning.py
GasNetSim/profile/StandardLoadProfile/slp_generator.py
GasNetSim/profile/StandardLoadProfile/data/EFH_sigmoid.csv
GasNetSim/profile/StandardLoadProfile/data/Einfamilienhaeuser.csv
GasNetSim/profile/StandardLoadProfile/data/Gewerbe_Fri.csv
gasnetsim-0.2.1.dist-info/METADATA
gasnetsim-0.2.1.dist-info/WHEEL
gasnetsim-0.2.1.dist-info/licenses/LICENSE
gasnetsim-0.2.1.dist-info/RECORD
