Metadata-Version: 2.4
Name: GasNetSim
Version: 0.2.1
Summary: A tool for gas network steady-state simulation.
Project-URL: Homepage, https://jugit.fz-juelich.de/iek-10/public/simulation/gasnetsim
Project-URL: Bug Tracker, https://jugit.fz-juelich.de/iek-10/public/simulation/gasnetsim/-/issues
Author-email: "ICE-1: Energy Systems Engineering, Forschungszentrum Jülich GmbH" <yifei.lu@fz-juelich.de>
Maintainer-email: Yifei Lu <yifei.lu@fz-juelich.de>
License: MPL-2.0
License-File: LICENSE
Keywords: energy systems,gas network,simulation
Classifier: License :: OSI Approved :: Mozilla Public License 2.0 (MPL 2.0)
Classifier: Operating System :: OS Independent
Classifier: Programming Language :: Python :: 3.9
Classifier: Programming Language :: Python :: 3.10
Classifier: Programming Language :: Python :: 3.11
Classifier: Programming Language :: Python :: 3.12
Classifier: Topic :: Scientific/Engineering
Requires-Python: <3.13,>=3.9
Requires-Dist: cantera~=3.0.0
Requires-Dist: cartopy>=0.24.1; python_version >= '3.10'
Requires-Dist: contextily>=1.6.2
Requires-Dist: geopandas>=1.0.1
Requires-Dist: jupyter>=1.1.1
Requires-Dist: matplotlib>=3.3.2
Requires-Dist: networkx==3.2.1
Requires-Dist: numba>=0.58.1
Requires-Dist: numpy<2.0.0,>=1.19.2
Requires-Dist: openpyxl>=3.1.5
Requires-Dist: pandas>=1.1.3
Requires-Dist: plotly>=5.23.0
Requires-Dist: pyarrow>=17.0.0
Requires-Dist: pyparsing~=3.0.7
Requires-Dist: pytest>=6.2.5
Requires-Dist: requests>=2.25.1
Requires-Dist: scipy>=1.5.2
Requires-Dist: seaborn>=0.12.2
Requires-Dist: setuptools>=60.9.3
Requires-Dist: shapely>=2.0.6
Requires-Dist: tqdm>=4.64.1
